
{   "Arson001_x264":{
        "Vandalism":[[1088,1339]],
        "Arson":[[1576,3427]],
        "Explosion":[[3480,3458]]
},
    "Arson002_x264":{
        "Arson":[[1850,2910]],
        "Explosion":[[2820,4441]],
        "Vandalism":[[190,1100],[1440,1760]]
    },
    "Arson003_x264":{
        "Arson":[[177,503]],
        "Explosion":[[901,2702],[2841,4014]]
    },
    "Arson005_x264":{
        "Arson":[[87,500]],
        "Explosion":[[639,2817]]
    },
    "Arson006_x264":{
        "Arson":[[675,1992]],
        "Explosion":[[2211,2615]]
    },
    "Arson007_x264":{
        "Arson":[[1200,5864]]
    },
    "Arson008_x264":{
        "Arson":[[26,346],[544,871]],
        "Explosion":[[382,483],[961,1014]]
    },
    "Arson009_x264":{
        "Arson":[[40,295]],
        "Explosion":[[321,336]]
    },
    "Arson010_x264":{
        "Vandalism":[[683,766],[2101,2204]],
        "Arson":[[894,1225],[2366,2704]]
    },
    "Arson011_x264":{
        "Arson":[[136,433],[678,1250]]
    },
    "Arson012_x264":{
        "Arson":[[35,172]],
        "Explosion":[[168,225]]  
    },
    "Arson013_x264":{
        "Arson":[[5316,5891]]
    },
    "Arson014_x264":{
        "Arson":[[543,1234]],
        "Explosion":[[1049,2369]]
    },
    "Arson015_x264":{
       "Vandalism":[[817,5432]],
       "Arson":[[6178,6953],[8404,8814]],
       "Explosion":[[7034,8035],[9715,10231]]
    },
    "Arson016_x264":{
        "Arson":[[321,847]],
        "Explosion":[[1263,1796]]
    },
    "Arson017_x264":{
        "Arson":[[432,585]],
        "Explosion":[[815,1210]]
    },
    "Arson018_x264":{
        "Arson":[[138,802]]
    },
    "Arson019_x264":{
        "Arson":[[10521,10778]],
        "Explosion":[[12404,28191]]
    },
    "Arson020_x264":{
        "Arson":[[1400,1740]],
        "Explosion":[[1620,2428]]
    }, 
    "Arson021_x264":{
        "Arson":[[296,1241]],
        "Explosion":[[1113,1441]]
    }, 
    "Arson022_x264":{
        "Arson":[[1060,4515]],
        "Explosion":[[5283,8640]]
    },
    "Arson023_x264":{
        "Arson":[[124,1348]],
        "Explosion":[[1302,1368]]
    },
    "Arson024_x264":{
        "Arson":[[1253,1446]],
        "Explosion":[[1023,5283]]
    },
    "Arson025_x264":{
        "Arson":[[842,1406]],
        "Explosion":[[1154,5283]]
    },
    "Arson026_x264":{
        "Arson":[[781,927]],
        "Explosion":[[3013,5899]]
    },
    "Arson027_x264":{
        "Arson":[[849,1592]],
        "Explosion":[[1788,2700]]
    },
    "Arson028_x264":{
    "Arson":[[1645,2030]],
    "Explosion":[[1695,2409]]
     },
     "Arson029_x264":{
        "Arson":[[491,1163]],
        "Explosion":[[792,1349]]
     },
     "Arson030_x264":{
        "Arson":[[478,4765]]
     },
     "Arson031_x264":{
        "Arson":[[176,1256]],
        "Explosion":[[1261,2828]]
     },
     "Arson032_x264":{
        "Arson":[[102,566],[737,1128],[1865,1951],[2364,2435]],
        "Explosion":[[257,694],[834,1178],[1868,2079],[2375,2767]],
        "RoadAccidents":[[1311,1398]]
     },
     "Arson034_x264":{
        "Vandalism":[[74,244]],
        "Fighting":[[352,538],[610,1183],[1546,1801]],
        "Arson":[[1163,2165]]
        
     },
     "Arson035_x264":{
        "Arson":[[427,1164]],
        "Explosion":[[698,789],[1099,1310]]
     },
     "Arson036_x264":{
        "Arson":[[28,290],[1152,1420]],
        "Explosion":[[1574,1699]]
     },
     "Arson037_x264":{
        "Arson":[[183,243],[352,450]],
        "Explosion":[[401,803]]
     },
     "Arson038_x264":{
        "Arson":[[37,309]],
        "Explosion":[[468,624]]
     },
     "Arson039_x264":{
        "Arson":[[1,305],[2326,2610]],
        
        "Fighting":[[413,868],[2739,3170]]
     },
     "Arson040_x264":{
        "Arson":[[73,383],[1054,1370]],
        "Explosion":[[337,531],[1326,2835]]
     },
     "Arson041_x264":{
        "Arson":[[2098,2954]],
        "Explosion":[[3467,3756]]
     },
     "Arson042_x264":{
        "Arson":[[3279,3560],[4029,4864]],
        "Explosion":[[5374,5875]]
     },
     "Arson044_x264":{
        "Arson":[[102,777]],
        "Explosion":[[605,1197]]
     },
     "Arson045_x264":{
        "Arson":[[495,846],[1185,1387],[2221,2640],[3571,3649]],
        "Explosion":[[3582,3753]]
     },
     "Arson046_x264":{
        "Arson":[[291,1920]],
        "Explosion":[[1938,2074]]
     },
     "Arson047_x264":{
        "Arson":[[467,617]],
        "Explosion":[[735,1444]]
     },
     "Arson048_x264":{
        "Explosion":[[195,414]],
        "Arson":[[76,200]]
     },
     "Arson049_x264":{ 
        "Arson":[[87,348]],
        "Explosion":[[131,387]]
     },
     "Arson050_x264":{
        "Vandalism":[[95,1005]],
        "Explosion":[[885,1583]],
        "Arson":[[880,971]]
     },
     "Arson051_x264":{
        "Arson":[[273,720]],
        "Explosion":[[600,719]]
     },
     "Arson052_x264":{
        "Explosion":[[1217,1315]],
        "Arson":[[950,1315]]
        
     },
     "Arson053_x264":{
        "Arson":[[22,1989],[2716,3035],[3719,3876],[4367,5238],[5651,6674]],
        "Explosion":[[4370,5341]]
     }

    
}      
    